{
  "jobs": [
    {
      "name": "Job1",
      "completed": true,
      "snapshot_date": "2024-01-05",
      "job_frequency": "Daily",
      "dependencies": []
    },
    {
      "name": "Job2",
      "completed": true,
      "snapshot_date": "2024-01-05",
      "job_frequency": "Daily",
      "dependencies": [
        "Job1"
      ]
    },
    {
      "name": "Job3",
      "completed": true,
      "snapshot_date": "2024-01-05",
      "job_frequency": "Daily",
      "dependencies": [
        "Job2"
      ]
    },
    {
      "name": "Job4",
      "completed": true,
      "snapshot_date": "2024-01-05",
      "job_frequency": null,
      "dependencies": [
        "Job1",
        "Job3"
      ]
    },
    {
      "name": "Job5",
      "completed": false,
      "snapshot_date": "2024-01-01",
      "job_frequency": null,
      "dependencies": []
    },
    {
      "name": "Job6",
      "completed": false,
      "snapshot_date": "2024-01-05",
      "job_frequency": null,
      "dependencies": [
        "Job1",
        "Job5"
      ]
    }
  ]
}